pygramm/__init__.py
pygramm/antlr.lark
pygramm/biased_choice.py
pygramm/binary_choice.py
pygramm/char_classes.py
pygramm/config.py
pygramm/generator.py
pygramm/grammar.py
pygramm/grammar_bias.py
pygramm/grammar_prune.py
pygramm/lex.py
pygramm/llparse.py
pygramm/unit_productions.py
pygramm-0.0.2.dist-info/METADATA
pygramm-0.0.2.dist-info/WHEEL
pygramm-0.0.2.dist-info/licenses/LICENSE.md
pygramm-0.0.2.dist-info/RECORD
