Metadata-Version: 2.1
Name: pygramm
Version: 0.0.2
Summary: Grammar library specialized for generating phrases (e.g., in fuzzing)
Project-URL: Homepage, https://github.com/uo-se-research/pygramm
Author-email: Michal Young <michal@cs.uoregon.edu>, Ziyad Alsaeed <zalsaeed@qu.edu.sa>
License-File: LICENSE.md
Classifier: License :: OSI Approved :: MIT License
Classifier: Operating System :: OS Independent
Classifier: Programming Language :: Python :: 3
Requires-Python: >=3.9
Requires-Dist: lark
Requires-Dist: pyyaml
